standardize_df/__init__.py
standardize_df/adjust_df.py
standardize_df/df_operations.py
standardize_df/pipeline.py
standardize_df/standards.py
standardize_df/utils.py
standardize_df-0.0.1.dist-info/LICENSE
standardize_df-0.0.1.dist-info/METADATA
standardize_df-0.0.1.dist-info/WHEEL
standardize_df-0.0.1.dist-info/top_level.txt
standardize_df-0.0.1.dist-info/RECORD
