Metadata-Version: 2.1
Name: standardize-df
Version: 0.0.1
Summary: Provides features to store and execute your operations for standardizing a pandas dataframes.
Home-page: https://github.com/yohan10/standardize-df
Author: Yohan Kim
Author-email: yohankimchi@gmail.com
License: BSD
Classifier: License :: OSI Approved :: BSD License
Classifier: Programming Language :: Python
Classifier: Programming Language :: Python :: 3
Classifier: Programming Language :: Python :: 3 :: Only
Requires-Python: >=3.6
License-File: LICENSE
Requires-Dist: pandas (>=1.4.0)
Provides-Extra: dev
Requires-Dist: numpy (>=1.22') ; extra == 'dev'
